src/Digital_Clock/Beep/lib/CW_DFF.v
// The MIT License (MIT)
// Copyright © 2023 <copyright C.W.>

// Permission is hereby granted, free of charge, to any person obtaining a copy of this software
// and associated documentation files (the “Software”), to deal in the Software withOut restriction,
// including withOut limitation the rights to use, copy, modify, merge, publish, distribute, sublicense,
// and/or sell copies of the Software, and to permit persons to whom the Software is furnished to do so, subject to the following conditions:

// The above copyright notice and this permission notice shall be included in all copies or substantial portions of the Software.

// THE SOFTWARE IS PROVIDED “AS IS”, WITHOut WARRANTY OF ANY KIND, EXPRESS OR IMPLIED, 
// INCLUDING BUT NOT LIMITED TO THE WARRANTIES OF MERCHANTABILITY, FITNESS FOR A PARTICULAR PURPOSE AND NONINFRINGEMENT. 
// IN NO EVENT SHALL THE AUTHORS OR COPYRIGHT HOLDERS BE LIABLE FOR ANY CLAIM, DAMAGES OR OTHER LIABILITY, 
// WHETHER IN AN ACTION OF CONTRACT, TORT OR OTHERWISE, ARISING FROM, 
// Out OF OR IN CONNECTION WITH THE SOFTWARE OR THE USE OR OTHER DEALINGS IN THE SOFTWARE.


module CW_DFF ( i_Clk , i_Din , o_Qout );
	
    parameter n = 4;  
	
    input   i_Clk;
	input   [ n -1 :0 ]  i_Din;
	output  [ n -1 :0 ]  o_Qout;
	
    reg     [ n -1 :0 ]  o_Qout;
	
	always @ ( posedge i_Clk )
    
		o_Qout <= i_Din;
        
endmodule

src/Digital_Clock/Beep/lib/Timer1.v
`define T1_WIDTH 3
`define T1_ON 3'd2
`define T1_OFF  3'd1
//响0.3秒停0.2秒
module Timer1(clk, rst, tload, tsel, done) ;
  parameter n=`T1_WIDTH ;
  input clk, rst, tload, tsel ;
  output done ;
  wire [n-1:0] count ; 
  reg  [n-1:0] next_count ;
  // state register
  CW_DFF  #(n) state(clk, next_count, count) ;
  // signal done
  assign done = ~(|count) ; 
// done = count == `T_WIDTH'b0  ? 1:0;
  // next count logic
  always@(*) begin
    casex({rst, tload, tsel, done})
      4'b1xxx: next_count = `T1_WIDTH'b0 ;
      4'b011x: next_count = `T1_ON ;
      4'b010x: next_count = `T1_OFF ;
      4'b00x0: next_count = count - 3'b1 ;
      4'b00x1: next_count = count ;
      default: next_count = count ;
    endcase
  end
endmodule

src/Digital_Clock/Beep/Flash.v

// define states for flash1
`define SWIDTH 4
`define S_OFF   4'b0000
`define S_A     4'b0001
`define S_B     4'b0010
`define S_C     4'b0011
`define S_D     4'b0100
`define S_E     4'b0101
`define S_OFF_1 4'b1001
`define S_OFF_2 4'b1010
`define S_OFF_3 4'b1011
`define S_OFF_4 4'b1100
`define S_OFF_5 4'b1101
`define S_OFF_6 4'b1110
`define S_OFF_7 4'b1111
`define S_OFF_8 4'b1000
`define S_OFF_9 4'b0111

//----------------------------------------------------------------------
// Flash module
//----------------------------------------------------------------------
module Flash(clk, rst, in, out) ;
  input clk, rst, in ; // in triggers start of flash sequence
  output out ;	       // out drives LED
  reg  out ;                       // output
  wire [`SWIDTH-1:0] state, next ; // current state
  reg  [`SWIDTH-1:0] next1  ;      // next state without reset
  reg  tload, tsel ;               // timer inputs
  wire done ;                      // timer output

  // instantiate state register
  CW_DFF #(`SWIDTH) state_reg(clk, next, state) ;

  // instantiate timer
  Timer1 timer(clk, rst, tload, tsel, done) ;

  always @(*) begin
    case(state) 
      `S_OFF: {out, tload, tsel, next1} = 
              {1'b0, 1'b1, 1'b1, in ? `S_A : `S_OFF } ;
      `S_A:   {out, tload, tsel, next1} = 
              {1'b1, done, 1'b0, done ? `S_B : `S_A } ;
      `S_B:   {out, tload, tsel, next1} = 
              {1'b0, done, 1'b1, done ? `S_C : `S_B } ;
      `S_C:   {out, tload, tsel, next1} = 
              {1'b1, done, 1'b0, done ? `S_D : `S_C } ;
      `S_D:   {out, tload, tsel, next1} = 
              {1'b0, done, 1'b1, done ? `S_E : `S_D } ;
      `S_E:   {out, tload, tsel, next1} = 
              {1'b1, done, 1'b1, done ? `S_OFF_1 : `S_E } ;

      `S_OFF_1 :{out, tload, tsel, next1} = 
              {1'b0, 1'b1, 1'b1, `S_OFF_2 } ;
      `S_OFF_2 :{out, tload, tsel, next1} = 
              {1'b0, 1'b1, 1'b1, `S_OFF_3 } ;
      `S_OFF_3 :{out, tload, tsel, next1} = 
              {1'b0, 1'b1, 1'b1, `S_OFF_4 } ;
      `S_OFF_4 :{out, tload, tsel, next1} = 
              {1'b0, 1'b1, 1'b1, `S_OFF_5 } ;
      `S_OFF_5 :{out, tload, tsel, next1} = 
              {1'b0, 1'b1, 1'b1, `S_OFF_6 } ;
        `S_OFF_6 :{out, tload, tsel, next1} = 
              {1'b0, 1'b1, 1'b1, `S_OFF_7 } ;
        `S_OFF_7 :{out, tload, tsel, next1} = 
              {1'b0, 1'b1, 1'b1, `S_OFF_8 } ;
        `S_OFF_8 :{out, tload, tsel, next1} = 
              {1'b0, 1'b1, 1'b1, `S_OFF_9 } ;
        `S_OFF_9 :{out, tload, tsel, next1} = 
              {1'b0, 1'b1, 1'b1, `S_OFF } ;
      default:{out, tload, tsel, next1} = 
              {1'b1, done, 1'b1, done ? `S_OFF : `S_E } ;
    endcase
  end

  assign next = rst ? `S_OFF : next1 ;
endmodule

src/Digital_Clock/Beep/Flash_TB.v
`timescale 1ns / 1ps  

`define SWIDTH 4
 
module Flash_TB();  
  

  
    // Testbench signals  
    reg clk;  
    reg rst;  
    reg in;  
    wire out;  
    wire [`SWIDTH-1:0] state; // Assuming we can observe the internal state for test purposes  
  
    // Instantiate the Flash module  
    Flash flash_dut(  
        .clk(clk),  
        .rst(rst),  
        .in(in),  
        .out(out)  
        // Assuming we can add an output for the state for test purposes  
        // .state(state) // Uncomment this if you have an output for state in your Flash module  
    );  
  
    // Clock generation  
    initial begin  
        clk = 0;  
        forever #5 clk = ~clk; // Assuming a 100MHz clock (5ns period)  
    end  
  
    // Test sequence  
    initial begin  
        // Initialize  
        rst = 1;  
        in = 0;  
        #10 rst = 0; // Apply reset for 10ns  
  
        // Test sequence A to OFF_1  
        in = 1; #10; // Trigger start of sequence  
        in = 0; #50; // Wait for sequence to complete (assuming timer duration is ~40ns)  
  
        // Test other states if needed...  
  
        // Finish the test  
        #100 $finish;  
    end  
  
    // Optionally, you can add assertions to check the behavior of out and state  
    // For example:  
    // initial begin  
    //     // ... (Assertions for specific states and outputs)  
    // end  
  
  initial begin
  // 打开VCD文件以记录信号变化  
    $dumpfile("Flash_TB.vcd");  
    // 开始记录所有当前可见的变量和内存  
    $dumpvars(0, Flash_TB); // 0表示所有层次，top_level_module是顶层模块的名字  
  end
endmodule

src/Digital_Clock/Beep/Flash_TB.vcd
$date
	Wed Jun 05 19:22:46 2024
$end
$version
	Icarus Verilog
$end
$timescale
	1ps
$end
$scope module Flash_TB $end
$var wire 1 ! out $end
$var reg 1 " clk $end
$var reg 1 # in $end
$var reg 1 $ rst $end
$scope module flash_dut $end
$var wire 1 " clk $end
$var wire 1 # in $end
$var wire 1 $ rst $end
$var wire 4 % state [3:0] $end
$var wire 4 & next [3:0] $end
$var wire 1 ' done $end
$var reg 4 ( next1 [3:0] $end
$var reg 1 ! out $end
$var reg 1 ) tload $end
$var reg 1 * tsel $end
$scope module state_reg $end
$var wire 1 " i_Clk $end
$var wire 4 + i_Din [3:0] $end
$var parameter 32 , n $end
$var reg 4 - o_Qout [3:0] $end
$upscope $end
$scope module timer $end
$var wire 1 " clk $end
$var wire 1 ' done $end
$var wire 1 $ rst $end
$var wire 1 ) tload $end
$var wire 1 * tsel $end
$var wire 3 . count [2:0] $end
$var parameter 32 / n $end
$var reg 3 0 next_count [2:0] $end
$scope module state $end
$var wire 1 " i_Clk $end
$var wire 3 1 i_Din [2:0] $end
$var parameter 32 2 n $end
$var reg 3 3 o_Qout [2:0] $end
$upscope $end
$upscope $end
$upscope $end
$upscope $end
$enddefinitions $end
$comment Show the parameter values. $end
$dumpall
b11 2
b11 /
b100 ,
$end
#0
$dumpvars
bx 3
b0 1
b0 0
bx .
bx -
b0 +
1*
x)
b0x0x (
x'
b0 &
bx %
1$
0#
0"
1!
$end
#5000
0!
1)
b0 (
1'
b0 %
b0 -
b0 .
b0 3
1"
#10000
b1 &
b1 +
b1 (
b10 0
b10 1
0"
1#
0$
#15000
0)
b1 &
b1 +
0'
b1 0
b1 1
1!
0*
b1 (
b10 .
b10 3
b1 %
b1 -
1"
#20000
0"
0#
#25000
b0 0
b0 1
b1 .
b1 3
1"
#30000
0"
#35000
b10 &
b10 +
1)
b10 (
1'
b1 0
b1 1
b0 .
b0 3
1"
#40000
0"
#45000
b0 0
b0 1
0!
0)
1*
0'
b10 %
b10 -
b1 .
b1 3
1"
#50000
0"
#55000
b11 &
b11 +
1)
b11 (
1'
b10 0
b10 1
b0 .
b0 3
1"
#60000
0"
#65000
b1 0
b1 1
1!
0)
0*
0'
b11 %
b11 -
b10 .
b10 3
1"
#70000
0"
#75000
b0 0
b0 1
b1 .
b1 3
1"
#80000
0"
#85000
b100 &
b100 +
1)
b100 (
1'
b1 0
b1 1
b0 .
b0 3
1"
#90000
0"
#95000
0)
b100 &
b100 +
0'
b0 0
b0 1
0!
1*
b100 (
b1 .
b1 3
b100 %
b100 -
1"
#100000
0"
#105000
b101 &
b101 +
1)
b101 (
1'
b10 0
b10 1
b0 .
b0 3
1"
#110000
0"
#115000
b1 0
b1 1
0)
b101 &
b101 +
0'
1!
b101 (
b10 .
b10 3
b101 %
b101 -
1"
#120000
0"
#125000
b0 0
b0 1
b1 .
b1 3
1"
#130000
0"
#135000
b1001 &
b1001 +
1)
b1001 (
1'
b10 0
b10 1
b0 .
b0 3
1"
#140000
0"
#145000
b1010 &
b1010 +
0!
b1010 (
0'
b1001 %
b1001 -
b10 .
b10 3
1"
#150000
0"
#155000
b1011 &
b1011 +
b1011 (
b1010 %
b1010 -
1"
#160000
0"
#165000
b1100 &
b1100 +
b1100 (
b1011 %
b1011 -
1"
